kybox/__init__.py
kybox/csv_util.py
kybox/des_util.py
kybox/excel_util.py
kybox/mysql_util.py
kybox/swagger_util.py
runcat/__init__.py
runcat/csv_util.py
runcat/des_util.py
runcat/excel_util.py
runcat/mysql_util.py
runcat/swagger_util.py
runcat-0.0.4.dist-info/METADATA
runcat-0.0.4.dist-info/WHEEL
runcat-0.0.4.dist-info/top_level.txt
runcat-0.0.4.dist-info/RECORD
