Metadata-Version: 2.1
Name: runcat
Version: 0.0.4
Summary: 常用工具库
Home-page: https://gitee.com/bluepang2021/runcat
Author: 杨康
Author-email: 772840356@qq.com
Platform: PC
Classifier: Programming Language :: Python :: 3.9
Requires-Python: >=3.9
Requires-Dist: pandas (==1.3.4)
Requires-Dist: openpyxl (==3.0.9)
Requires-Dist: pycryptodome (==3.14.1)
Requires-Dist: PyMySQL (==0.10.1)
Requires-Dist: requests (==2.31.0)
Provides-Extra: des
Requires-Dist: pycryptodome (==3.14.1) ; extra == 'des'
Provides-Extra: excel
Requires-Dist: pandas (==1.3.4) ; extra == 'excel'
Requires-Dist: openpyxl (==3.0.9) ; extra == 'excel'
Provides-Extra: mysql
Requires-Dist: PyMySQL (==0.10.1) ; extra == 'mysql'
Provides-Extra: swagger
Requires-Dist: requests (==2.31.0) ; extra == 'swagger'
